furthrmind_sdk/__init__.py
furthrmind_sdk/collection/__init__.py
furthrmind_sdk/collection/baseclass.py
furthrmind_sdk/collection/category.py
furthrmind_sdk/collection/column.py
furthrmind_sdk/collection/comboboxentry.py
furthrmind_sdk/collection/datatable.py
furthrmind_sdk/collection/experiment.py
furthrmind_sdk/collection/field.py
furthrmind_sdk/collection/fielddata.py
furthrmind_sdk/collection/file.py
furthrmind_sdk/collection/group.py
furthrmind_sdk/collection/import_collection.py
furthrmind_sdk/collection/project.py
furthrmind_sdk/collection/researchitem.py
furthrmind_sdk/collection/sample.py
furthrmind_sdk/collection/unit.py
furthrmind_sdk/file_loader.py
furthrmind_sdk/furthrmind.py
furthrmind_sdk/utils.py
furthrmind_sdk-0.1a10.dist-info/LICENSE
furthrmind_sdk-0.1a10.dist-info/METADATA
furthrmind_sdk-0.1a10.dist-info/WHEEL
furthrmind_sdk-0.1a10.dist-info/RECORD
