Metadata-Version: 2.1
Name: furthrmind-sdk
Version: 0.1a10
Summary: Official python wrapper for the FURTHRmind rest api.
Home-page: https://github.com/FURTHRresearch/furthrmind-sdk
License: GNU GENERAL PUBLIC LICENSE Version 3
Author: Daniel Menne
Requires-Python: >=3.10,<4.0
Classifier: License :: Other/Proprietary License
Classifier: Programming Language :: Python :: 3
Classifier: Programming Language :: Python :: 3.10
Classifier: Programming Language :: Python :: 3.11
Classifier: Programming Language :: Python :: 3.12
Requires-Dist: pandas (>=2.2.1,<3.0.0)
Requires-Dist: pathvalidate (>=3.2.0,<4.0.0)
Requires-Dist: pymongo (>=4.6.2,<5.0.0)
Requires-Dist: requests
Requires-Dist: typing-extensions (>=4.10.0,<5.0.0)
Project-URL: Repository, https://github.com/FURTHRresearch/furthrmind-sdk
